chemix/__init__.py
chemix/solution.py
tests/__init__.py
tests/test_chemix.py
chemix-0.0.1.dist-info/LICENSE
chemix-0.0.1.dist-info/METADATA
chemix-0.0.1.dist-info/WHEEL
chemix-0.0.1.dist-info/top_level.txt
chemix-0.0.1.dist-info/RECORD
